LICENSE.txt
MANIFEST.in
README.md
pyproject.toml
setup.py
seislib/__init__.py
seislib/__version__.py
seislib.egg-info/PKG-INFO
seislib.egg-info/SOURCES.txt
seislib.egg-info/dependency_links.txt
seislib.egg-info/requires.txt
seislib.egg-info/top_level.txt
seislib/an/__init__.py
seislib/an/_an_attenuation.py
seislib/an/_an_downloader.py
seislib/an/_an_processing.py
seislib/an/_an_velocity.py
seislib/eq/__init__.py
seislib/eq/_eq_downloader.py
seislib/eq/_eq_velocity.py
seislib/exceptions/__init__.py
seislib/exceptions/_exceptions.py
seislib/plotting/__init__.py
seislib/plotting/_plotting.py
seislib/tomography/__init__.py
seislib/tomography/_grid.py
seislib/tomography/_tomography.py
seislib/tomography/_ray_theory/__init__.py
seislib/tomography/_ray_theory/_math.c
seislib/tomography/_ray_theory/_math.cpython-39-x86_64-linux-gnu.so
seislib/tomography/_ray_theory/_math.pxd
seislib/tomography/_ray_theory/_math.pyx
seislib/tomography/_ray_theory/_spherical_geometry.cpp
seislib/tomography/_ray_theory/_spherical_geometry.cpython-39-x86_64-linux-gnu.so
seislib/tomography/_ray_theory/_spherical_geometry.pxd
seislib/tomography/_ray_theory/_spherical_geometry.pyx
seislib/tomography/_ray_theory/_tomography.cpp
seislib/tomography/_ray_theory/_tomography.cpython-39-x86_64-linux-gnu.so
seislib/tomography/_ray_theory/_tomography.pyx
seislib/tomography/_ray_theory/setup_all.py
seislib/utils/__init__.py
seislib/utils/_utils.py