Metadata-Version: 2.1
Name: seislib
Version: 1.1.2
Summary: Multi-scale Seismic Imaging
Home-page: https://github.com/fmagrini/seislib
Author: Fabrizio Magrini
Author-email: fabrizio.magrini90@gmail.com
License: MIT
Keywords: Seismic Imaging,Surface Waves,Seismic Ambient Noise,Earthquake Seismology,Tomographic Inversion
Platform: UNKNOWN
Classifier: License :: OSI Approved :: MIT License
Classifier: Programming Language :: Python :: 3
Classifier: Programming Language :: Cython
Requires-Python: >=3.6
License-File: LICENSE.txt
